ostryalis/__init__.py
ostryalis/cli.py
ostryalis/database.py
ostryalis/read.py
ostryalis/search.py
ostryalis-0.2.1.dist-info/METADATA
ostryalis-0.2.1.dist-info/WHEEL
ostryalis-0.2.1.dist-info/entry_points.txt
ostryalis-0.2.1.dist-info/RECORD
