Metadata-Version: 2.4
Name: ostryalis
Version: 0.2.1
Summary: object store
Author-email: Hans Gremmen <hans@leptonix.net>
License: MIT
Requires-Python: >=3.11
Requires-Dist: aiosqlite>=0.20
Requires-Dist: inceptum>=0.8.2
Requires-Dist: sqlalchemy>=2
Requires-Dist: typer>=0.12
